{
   "agent": "PocketSocketServer",
   "behavior": "OK",
   "behaviorClose": "OK",
   "case": 420,
   "closedByMe": true,
   "createStats": true,
   "createWirelog": true,
   "description": "Send 1000 compressed messages each of payload size 65536, auto-fragment to 0 octets. Use permessage-deflate client offers (requestNoContextTakeover, requestMaxWindowBits): [(True, 0)]",
   "droppedByMe": false,
   "duration": 3059,
   "expectation": "Receive echo'ed messages (with payload as sent). Timeout case after 480 secs.",
   "expected": {},
   "expectedClose": {
      "closeCode": [
         1000
      ],
      "closedByMe": true,
      "requireClean": true
   },
   "failedByMe": false,
   "httpRequest": "GET / HTTP/1.1\r\nUser-Agent: AutobahnTestSuite/0.7.5-0.10.9\r\nHost: 127.0.0.1:9001\r\nUpgrade: WebSocket\r\nConnection: Upgrade\r\nPragma: no-cache\r\nCache-Control: no-cache\r\nSec-WebSocket-Key: sRE4s8hf42dpsTlzDryzQw==\r\nSec-WebSocket-Extensions: permessage-deflate; client_no_context_takeover; client_max_window_bits; server_no_context_takeover\r\nSec-WebSocket-Version: 13\r\n\r\n",
   "httpResponse": "HTTP/1.1 101 Switching Protocols\r\nSec-WebSocket-Accept: asboOV0M5fCJi3S3OSkMIrVR8Yo=\r\nSec-WebSocket-Extensions: permessage-deflate; client_max_window_bits=15; server_max_window_bits=15\r\nUpgrade: websocket\r\nConnection: Upgrade\r\n\r\n",
   "id": "13.2.9",
   "isServer": false,
   "localCloseCode": 1000,
   "localCloseReason": null,
   "received": [],
   "remoteCloseCode": 1000,
   "remoteCloseReason": null,
   "reportCompressionRatio": true,
   "reportTime": true,
   "result": "Ok, received all echo'ed messages in time.",
   "resultClose": "Connection was properly closed",
   "rxFrameStats": {
      "1": 1000,
      "8": 1
   },
   "rxOctetStats": {
      "2": 2,
      "4": 47,
      "229": 1,
      "3504": 1,
      "3505": 2,
      "3506": 2,
      "3507": 5,
      "3508": 2,
      "3509": 1,
      "3510": 10,
      "3511": 6,
      "3512": 7,
      "3513": 18,
      "3514": 8,
      "3515": 9,
      "3516": 16,
      "3517": 9,
      "3518": 13,
      "3519": 16,
      "3520": 12,
      "3521": 17,
      "3522": 11,
      "3523": 18,
      "3524": 15,
      "3525": 13,
      "3526": 17,
      "3527": 17,
      "3528": 7,
      "3529": 18,
      "3530": 11,
      "3531": 15,
      "3532": 14,
      "3533": 15,
      "3534": 9,
      "3535": 10,
      "3536": 16,
      "3537": 14,
      "3538": 11,
      "3539": 12,
      "3540": 10,
      "3541": 14,
      "3542": 9,
      "3543": 10,
      "3544": 16,
      "3545": 14,
      "3546": 13,
      "3547": 5,
      "3548": 7,
      "3549": 5,
      "3550": 15,
      "3551": 7,
      "3552": 11,
      "3553": 7,
      "3554": 15,
      "3555": 10,
      "3556": 12,
      "3557": 7,
      "3558": 12,
      "3559": 8,
      "3560": 2,
      "3561": 5,
      "3562": 6,
      "3563": 2,
      "3564": 8,
      "3565": 5,
      "3566": 2,
      "3567": 1,
      "3569": 4,
      "3570": 3,
      "3571": 2,
      "3572": 4,
      "3573": 4,
      "3574": 2,
      "3575": 1,
      "3576": 3,
      "3577": 2,
      "3578": 4,
      "3579": 2,
      "3580": 1,
      "3581": 3,
      "3582": 4,
      "3583": 5,
      "3584": 6,
      "3585": 6,
      "3586": 6,
      "3587": 4,
      "3588": 4,
      "3589": 4,
      "3592": 1,
      "3593": 4,
      "3594": 2,
      "3595": 4,
      "3596": 3,
      "3597": 1,
      "3598": 4,
      "3599": 4,
      "3600": 2,
      "3601": 4,
      "3602": 2,
      "3603": 1,
      "3604": 3,
      "3605": 6,
      "3606": 6,
      "3607": 5,
      "3608": 3,
      "3609": 11,
      "3610": 13,
      "3611": 10,
      "3612": 12,
      "3613": 18,
      "3614": 11,
      "3615": 19,
      "3616": 10,
      "3617": 12,
      "3618": 8,
      "3619": 3,
      "3620": 10,
      "3621": 2,
      "3622": 7,
      "3623": 10,
      "3624": 4,
      "3625": 4,
      "3626": 4,
      "3628": 2,
      "3629": 1,
      "3630": 2,
      "3631": 2,
      "3632": 1,
      "3633": 2,
      "3634": 2,
      "3635": 7,
      "3636": 8,
      "3637": 5,
      "3638": 6,
      "3639": 3,
      "3640": 7,
      "3641": 6,
      "3642": 3,
      "3643": 8,
      "3644": 2,
      "3645": 1
   },
   "started": "2016-03-30T12:08:08.482Z",
   "trafficStats": {
      "incomingCompressionRatio": 0.05429566955566406,
      "incomingOctetsAppLevel": 65536000,
      "incomingOctetsWebSocketLevel": 3558321,
      "incomingOctetsWireLevel": 3562321,
      "incomingWebSocketFrames": 1000,
      "incomingWebSocketMessages": 1000,
      "incomingWebSocketOverhead": 0.0011241256761264653,
      "outgoingCompressionRatio": 0.04351942443847656,
      "outgoingOctetsAppLevel": 65536000,
      "outgoingOctetsWebSocketLevel": 2852089,
      "outgoingOctetsWireLevel": 2860089,
      "outgoingWebSocketFrames": 1000,
      "outgoingWebSocketMessages": 1000,
      "outgoingWebSocketOverhead": 0.0028049615562487705,
      "preopenIncomingOctetsWireLevel": 229,
      "preopenOutgoingOctetsWireLevel": 366
   },
   "txFrameStats": {
      "1": 1000,
      "8": 1
   },
   "txOctetStats": {
      "8": 1,
      "366": 1,
      "2805": 2,
      "2806": 1,
      "2807": 2,
      "2808": 5,
      "2809": 4,
      "2810": 6,
      "2811": 5,
      "2812": 6,
      "2813": 13,
      "2814": 16,
      "2815": 23,
      "2816": 25,
      "2817": 29,
      "2818": 18,
      "2819": 33,
      "2820": 19,
      "2821": 32,
      "2822": 20,
      "2823": 23,
      "2824": 17,
      "2825": 20,
      "2826": 27,
      "2827": 25,
      "2828": 22,
      "2829": 26,
      "2830": 20,
      "2831": 34,
      "2832": 20,
      "2833": 13,
      "2834": 8,
      "2835": 9,
      "2836": 17,
      "2837": 17,
      "2838": 17,
      "2839": 16,
      "2840": 10,
      "2841": 9,
      "2842": 5,
      "2843": 3,
      "2844": 1,
      "2845": 3,
      "2846": 4,
      "2847": 2,
      "2850": 2,
      "2851": 1,
      "2853": 1,
      "2854": 1,
      "2855": 2,
      "2857": 1,
      "2858": 1,
      "2859": 2,
      "2861": 3,
      "2863": 4,
      "2864": 1,
      "2866": 4,
      "2867": 3,
      "2868": 2,
      "2870": 2,
      "2871": 1,
      "2872": 1,
      "2873": 1,
      "2874": 1,
      "2876": 1,
      "2882": 1,
      "2883": 1,
      "2886": 2,
      "2887": 1,
      "2888": 1,
      "2889": 1,
      "2890": 2,
      "2891": 1,
      "2892": 2,
      "2896": 1,
      "2899": 1,
      "2901": 1,
      "2903": 3,
      "2904": 2,
      "2905": 2,
      "2906": 5,
      "2907": 8,
      "2908": 5,
      "2909": 7,
      "2910": 4,
      "2911": 7,
      "2912": 2,
      "2913": 4,
      "2914": 3,
      "2915": 4,
      "2916": 11,
      "2917": 11,
      "2918": 16,
      "2919": 10,
      "2920": 12,
      "2921": 6,
      "2922": 18,
      "2923": 12,
      "2924": 6,
      "2925": 9,
      "2926": 12,
      "2927": 12,
      "2928": 13,
      "2929": 8,
      "2930": 7,
      "2931": 9,
      "2932": 7,
      "2933": 6,
      "2934": 4,
      "2935": 4,
      "2936": 2,
      "2937": 4,
      "2938": 1,
      "2939": 4,
      "2940": 11,
      "2941": 8,
      "2942": 14,
      "2943": 10,
      "2944": 9,
      "2945": 5,
      "2946": 2,
      "2947": 3,
      "2961": 1
   },
   "wasClean": true,
   "wasCloseHandshakeTimeout": false,
   "wasNotCleanReason": null,
   "wasOpenHandshakeTimeout": false,
   "wasServerConnectionDropTimeout": false,
   "wirelog": [
      [
         "TO",
         [
            366,
            "474554202f20485454502f312e310d0a557365722d4167656e743a204175746f6261686e5465737453756974652f302e372e352d302e31302e390d0a486f7374 ..."
         ],
         false
      ],
      [
         "RO",
         [
            229,
            "485454502f312e312031303120537769746368696e672050726f746f636f6c730d0a5365632d576562536f636b65742d4163636570743a206173626f4f56304d ..."
         ]
      ],
      [
         "WLM",
         false
      ],
      [
         "TI",
         480
      ],
      [
         "WLM",
         true
      ],
      [
         "TF",
         [
            2,
            "0x03e8"
         ],
         8,
         true,
         0,
         "22b33877",
         null,
         null,
         false
      ],
      [
         "TO",
         [
            8,
            "888222b33877215b"
         ],
         false
      ],
      [
         "RO",
         [
            2,
            "8802"
         ]
      ],
      [
         "RO",
         [
            2,
            "03e8"
         ]
      ],
      [
         "RF",
         [
            2,
            "0x03e8"
         ],
         8,
         true,
         0,
         false,
         null
      ]
   ]
}