{
   "agent": "PocketSocketClient",
   "behavior": "OK",
   "behaviorClose": "OK",
   "case": 380,
   "closedByMe": true,
   "createStats": true,
   "createWirelog": true,
   "description": "Send 1000 compressed messages each of payload size 4096, auto-fragment to 0 octets. Use default permessage-deflate offer.",
   "droppedByMe": true,
   "duration": 741,
   "expectation": "Receive echo'ed messages (with payload as sent). Timeout case after 480 secs.",
   "expected": {},
   "expectedClose": {
      "closeCode": [
         1000
      ],
      "closedByMe": true,
      "requireClean": true
   },
   "failedByMe": false,
   "httpRequest": "GET /runCase?case=380&agent=PocketSocketClient HTTP/1.1\r\nHost: localhost:9001\r\nSec-WebSocket-Key: jqBMHXuImLDATq6GDT5IoA==\r\nSec-WebSocket-Version: 13\r\nUpgrade: websocket\r\nOrigin: http://localhost:9001\r\nSec-WebSocket-Extensions: permessage-deflate; client_max_window_bits\r\nConnection: upgrade\r\n\r\n",
   "httpResponse": "HTTP/1.1 101 Switching Protocols\r\nServer: AutobahnTestSuite/0.7.5-0.10.9\r\nX-Powered-By: AutobahnPython/0.10.9\r\nUpgrade: WebSocket\r\nConnection: Upgrade\r\nSec-WebSocket-Accept: 8UVXet5RB8t/4bH4zsBl77Cp9Ds=\r\nSec-WebSocket-Extensions: permessage-deflate\r\n\r\n",
   "id": "12.5.5",
   "isServer": true,
   "localCloseCode": 1000,
   "localCloseReason": null,
   "received": [],
   "remoteCloseCode": 1000,
   "remoteCloseReason": null,
   "reportCompressionRatio": true,
   "reportTime": true,
   "result": "Ok, received all echo'ed messages in time.",
   "resultClose": "Connection was properly closed",
   "rxFrameStats": {
      "2": 1000,
      "8": 1
   },
   "rxOctetStats": {
      "8": 24,
      "100": 1,
      "108": 1,
      "131": 1,
      "138": 1,
      "156": 1,
      "171": 1,
      "175": 1,
      "184": 2,
      "185": 1,
      "186": 2,
      "187": 1,
      "192": 2,
      "197": 1,
      "202": 2,
      "204": 1,
      "207": 2,
      "210": 1,
      "211": 1,
      "231": 1,
      "237": 1,
      "240": 1,
      "254": 1,
      "266": 1,
      "267": 1,
      "268": 1,
      "269": 1,
      "273": 1,
      "278": 2,
      "280": 1,
      "283": 1,
      "287": 1,
      "292": 1,
      "296": 1,
      "298": 1,
      "300": 1,
      "308": 1,
      "309": 1,
      "315": 1,
      "320": 1,
      "346": 1,
      "347": 1,
      "353": 1,
      "363": 2,
      "364": 1,
      "365": 1,
      "369": 2,
      "370": 2,
      "371": 1,
      "373": 2,
      "377": 1,
      "379": 1,
      "380": 1,
      "382": 1,
      "383": 3,
      "384": 1,
      "387": 1,
      "388": 1,
      "389": 1,
      "400": 1,
      "402": 1,
      "403": 1,
      "404": 1,
      "421": 1,
      "437": 1,
      "445": 1,
      "456": 1,
      "459": 1,
      "460": 1,
      "469": 1,
      "480": 2,
      "486": 1,
      "490": 1,
      "491": 1,
      "512": 1,
      "524": 1,
      "526": 1,
      "530": 1,
      "546": 1,
      "559": 1,
      "572": 1,
      "577": 2,
      "579": 1,
      "588": 1,
      "590": 1,
      "627": 1,
      "664": 1,
      "671": 1,
      "678": 1,
      "686": 1,
      "687": 1,
      "709": 1,
      "743": 1,
      "766": 1,
      "785": 1,
      "797": 1,
      "800": 1,
      "812": 1,
      "815": 1,
      "850": 1,
      "863": 1,
      "882": 1,
      "886": 1,
      "906": 1,
      "907": 1,
      "952": 1,
      "956": 1,
      "968": 1,
      "971": 1,
      "1011": 1,
      "1017": 1,
      "1050": 1,
      "1052": 1,
      "1057": 1,
      "1060": 1,
      "1063": 1,
      "1074": 1,
      "1075": 1,
      "1090": 1,
      "1104": 1,
      "1105": 1,
      "1108": 1,
      "1109": 1,
      "1110": 1,
      "1112": 1,
      "1128": 3,
      "1139": 1,
      "1160": 1,
      "1186": 1,
      "1215": 1,
      "1238": 1,
      "1244": 1,
      "1250": 1,
      "1252": 1,
      "1253": 1,
      "1257": 1,
      "1269": 1,
      "1271": 1,
      "1278": 1,
      "1293": 1,
      "1307": 1,
      "1336": 1,
      "1337": 1,
      "1357": 1,
      "1383": 1,
      "1403": 1,
      "1416": 1,
      "1433": 1,
      "1442": 1,
      "1452": 1,
      "1457": 1,
      "1467": 2,
      "1485": 1,
      "1512": 1,
      "1543": 1,
      "1560": 1,
      "1632": 1,
      "1641": 1,
      "1692": 1,
      "1786": 1,
      "1796": 2,
      "1800": 1,
      "1813": 1,
      "1867": 1,
      "1885": 1,
      "1912": 1,
      "1950": 2,
      "1951": 1,
      "2097": 1,
      "2107": 1,
      "2149": 1,
      "2151": 1,
      "2166": 1,
      "2295": 1,
      "2296": 1,
      "2426": 1,
      "2442": 1,
      "2464": 1,
      "2468": 1,
      "2473": 1,
      "2478": 1,
      "2500": 1,
      "2510": 1,
      "2515": 1,
      "2573": 1,
      "2576": 1,
      "2586": 1,
      "2594": 1,
      "2630": 1,
      "2636": 1,
      "2670": 1,
      "2682": 1,
      "2688": 1,
      "2715": 1,
      "2726": 1,
      "2735": 2,
      "2738": 1,
      "2746": 1,
      "2770": 1,
      "2777": 1,
      "2788": 1,
      "2802": 1,
      "2812": 1,
      "2813": 1,
      "2817": 1,
      "2831": 1,
      "2845": 1,
      "2846": 1,
      "2850": 1,
      "2859": 1,
      "2860": 1,
      "2919": 1,
      "2923": 1,
      "2951": 1,
      "2956": 1,
      "2969": 1,
      "2975": 1,
      "2980": 1,
      "2982": 1,
      "2987": 1,
      "2989": 1,
      "2990": 1,
      "2993": 1,
      "2999": 1,
      "3006": 1,
      "3009": 1,
      "3013": 1,
      "3015": 1,
      "3016": 2,
      "3018": 1,
      "3020": 1,
      "3023": 1,
      "3029": 1,
      "3035": 2,
      "3039": 1,
      "3040": 1,
      "3042": 1,
      "3044": 1,
      "3047": 2,
      "3049": 2,
      "3050": 1,
      "3059": 1,
      "3061": 1,
      "3063": 1,
      "3066": 1,
      "3069": 1,
      "3071": 1,
      "3075": 1,
      "3076": 1,
      "3079": 1,
      "3080": 1,
      "3081": 1,
      "3085": 1,
      "3086": 1,
      "3092": 1,
      "3095": 1,
      "3097": 1,
      "3098": 1,
      "3102": 1,
      "3126": 1,
      "3133": 1,
      "3134": 3,
      "3139": 1,
      "3141": 1,
      "3143": 1,
      "3148": 1,
      "3155": 1,
      "3157": 1,
      "3158": 2,
      "3159": 1,
      "3161": 1,
      "3172": 1,
      "3174": 2,
      "3176": 1,
      "3177": 1,
      "3182": 1,
      "3183": 1,
      "3187": 1,
      "3188": 1,
      "3190": 1,
      "3192": 1,
      "3196": 1,
      "3211": 1,
      "3215": 1,
      "3222": 1,
      "3232": 1,
      "3235": 1,
      "3248": 1,
      "3252": 1,
      "3254": 1,
      "3262": 1,
      "3264": 1,
      "3267": 2,
      "3281": 1,
      "3288": 1,
      "3290": 1,
      "3294": 1,
      "3297": 1,
      "3311": 1,
      "3316": 1,
      "3322": 2,
      "3324": 1,
      "3330": 1,
      "3335": 1,
      "3336": 2,
      "3369": 1,
      "3393": 1,
      "3402": 1,
      "3434": 1,
      "3471": 1,
      "3485": 1,
      "3496": 2,
      "3504": 1,
      "3517": 1,
      "3525": 1,
      "3534": 1,
      "3540": 1,
      "3541": 1,
      "3547": 1,
      "3577": 1,
      "3600": 1,
      "3633": 1,
      "3740": 1,
      "3741": 1,
      "3742": 2,
      "3745": 1,
      "3761": 1,
      "3789": 1,
      "3818": 1,
      "3819": 1,
      "3831": 1,
      "3839": 1,
      "3845": 1,
      "3856": 2,
      "3863": 1,
      "3865": 2,
      "3866": 1,
      "3872": 2,
      "3874": 1,
      "3876": 1,
      "3884": 1,
      "3885": 1,
      "3894": 1,
      "3896": 1,
      "3897": 1,
      "3898": 1,
      "3902": 1,
      "3904": 1,
      "3906": 2,
      "3916": 1,
      "3917": 2,
      "3918": 1,
      "3930": 1,
      "3931": 1,
      "3932": 1,
      "3934": 1,
      "3939": 1,
      "3941": 1,
      "3946": 1,
      "3953": 1,
      "3956": 1,
      "3963": 2,
      "3967": 1,
      "3968": 1,
      "3976": 1,
      "3979": 1,
      "3984": 2,
      "3987": 1,
      "3996": 2,
      "4001": 2,
      "4002": 1,
      "4008": 1,
      "4011": 1,
      "4015": 1,
      "4016": 1,
      "4017": 2,
      "4018": 1,
      "4019": 3,
      "4020": 1,
      "4022": 2,
      "4026": 1,
      "4029": 2,
      "4031": 1,
      "4032": 1,
      "4033": 1,
      "4034": 2,
      "4037": 3,
      "4038": 1,
      "4039": 2,
      "4040": 1,
      "4041": 1,
      "4046": 1,
      "4047": 2,
      "4051": 2,
      "4056": 2,
      "4057": 3,
      "4058": 1,
      "4059": 3,
      "4060": 3,
      "4061": 2,
      "4062": 3,
      "4063": 2,
      "4064": 1,
      "4065": 2,
      "4067": 2,
      "4068": 1,
      "4070": 2,
      "4071": 1,
      "4073": 3,
      "4078": 3,
      "4079": 4,
      "4080": 5,
      "4081": 3,
      "4082": 5,
      "4083": 3,
      "4084": 5,
      "4085": 2,
      "4086": 5,
      "4087": 4,
      "4089": 1,
      "4090": 7,
      "4091": 10,
      "4092": 4,
      "4093": 5,
      "4094": 3,
      "4095": 8,
      "4096": 5,
      "4097": 7,
      "4098": 4,
      "4099": 8,
      "4100": 1,
      "4101": 6,
      "4102": 7,
      "4103": 4,
      "4104": 5,
      "4105": 4,
      "4106": 2,
      "4107": 6,
      "4108": 3,
      "4109": 2,
      "4110": 144,
      "4111": 5,
      "4112": 4,
      "4113": 3,
      "4114": 4,
      "4115": 2,
      "4116": 5,
      "4117": 2,
      "4119": 1,
      "4120": 4,
      "4121": 6,
      "4123": 2,
      "4124": 3,
      "4125": 7,
      "4126": 1,
      "4127": 2,
      "4128": 5,
      "4129": 2,
      "4130": 4,
      "4131": 5,
      "4133": 1,
      "4134": 4,
      "4135": 3,
      "4136": 3,
      "4137": 5,
      "4138": 3,
      "4140": 4,
      "4141": 4,
      "4142": 2,
      "4143": 1,
      "4145": 1,
      "4146": 2,
      "4147": 2,
      "4148": 3,
      "4149": 2,
      "4150": 3,
      "4151": 4,
      "4152": 5,
      "4153": 2,
      "4154": 1,
      "4155": 3,
      "4156": 2,
      "4157": 2,
      "4158": 1,
      "4159": 3,
      "4160": 2,
      "4161": 1,
      "4162": 2,
      "4163": 3,
      "4164": 1,
      "4165": 1,
      "4167": 2,
      "4168": 2,
      "4169": 2,
      "4170": 2,
      "4171": 2,
      "4173": 3,
      "4174": 1,
      "4175": 6,
      "4176": 3,
      "4177": 2,
      "4178": 1,
      "4179": 1,
      "4181": 1,
      "4183": 2,
      "4184": 2,
      "4185": 3,
      "4186": 1,
      "4187": 1,
      "4190": 1,
      "4191": 2,
      "4192": 2,
      "4193": 1,
      "4196": 5,
      "4197": 3,
      "4198": 1,
      "4199": 1,
      "4204": 2,
      "4205": 1,
      "4207": 1,
      "4208": 3,
      "4209": 1,
      "4212": 1,
      "4215": 1,
      "4216": 2,
      "4218": 1,
      "4222": 2,
      "4224": 1,
      "4225": 1,
      "4229": 3,
      "4231": 1,
      "4234": 1,
      "4235": 3,
      "4239": 1,
      "4240": 1,
      "4241": 1,
      "4244": 2,
      "4245": 1,
      "4246": 1,
      "4247": 1,
      "4249": 2,
      "4253": 1,
      "4257": 1,
      "4260": 1,
      "4266": 1,
      "4268": 1,
      "4270": 1,
      "4271": 1,
      "4276": 1
   },
   "started": "2016-03-30T11:21:33.054Z",
   "trafficStats": {
      "incomingCompressionRatio": 0.80447119140625,
      "incomingOctetsAppLevel": 4096000,
      "incomingOctetsWebSocketLevel": 3295114,
      "incomingOctetsWireLevel": 3303108,
      "incomingWebSocketFrames": 1000,
      "incomingWebSocketMessages": 1000,
      "incomingWebSocketOverhead": 0.002426016216737873,
      "outgoingCompressionRatio": 0.7769853515625,
      "outgoingOctetsAppLevel": 4096000,
      "outgoingOctetsWebSocketLevel": 3182532,
      "outgoingOctetsWireLevel": 3186526,
      "outgoingWebSocketFrames": 1000,
      "outgoingWebSocketMessages": 1000,
      "outgoingWebSocketOverhead": 0.0012549755980458327,
      "preopenIncomingOctetsWireLevel": 300,
      "preopenOutgoingOctetsWireLevel": 252
   },
   "txFrameStats": {
      "2": 1000,
      "8": 1
   },
   "txOctetStats": {
      "4": 1,
      "96": 1,
      "104": 1,
      "127": 1,
      "134": 1,
      "150": 1,
      "167": 1,
      "171": 1,
      "179": 1,
      "180": 2,
      "182": 1,
      "183": 1,
      "188": 2,
      "189": 1,
      "193": 1,
      "198": 2,
      "200": 1,
      "203": 2,
      "206": 1,
      "207": 1,
      "227": 1,
      "233": 1,
      "236": 1,
      "242": 1,
      "250": 1,
      "252": 1,
      "254": 1,
      "256": 1,
      "259": 1,
      "263": 1,
      "264": 1,
      "265": 1,
      "270": 1,
      "274": 2,
      "277": 1,
      "279": 3,
      "283": 1,
      "284": 1,
      "285": 2,
      "288": 2,
      "290": 1,
      "291": 1,
      "292": 1,
      "293": 3,
      "294": 1,
      "296": 1,
      "300": 2,
      "301": 1,
      "303": 1,
      "308": 1,
      "309": 1,
      "310": 1,
      "326": 1,
      "341": 1,
      "351": 1,
      "352": 1,
      "359": 1,
      "369": 2,
      "372": 1,
      "378": 1,
      "383": 1,
      "384": 1,
      "388": 1,
      "402": 1,
      "418": 1,
      "432": 1,
      "441": 2,
      "442": 1,
      "450": 1,
      "452": 2,
      "456": 1,
      "475": 2,
      "482": 1,
      "484": 1,
      "493": 1,
      "511": 1,
      "513": 1,
      "514": 1,
      "520": 1,
      "526": 1,
      "559": 1,
      "573": 2,
      "586": 1,
      "612": 1,
      "615": 1,
      "616": 1,
      "630": 1,
      "648": 1,
      "663": 1,
      "667": 1,
      "668": 1,
      "722": 1,
      "744": 1,
      "752": 1,
      "760": 1,
      "774": 1,
      "781": 1,
      "803": 2,
      "805": 1,
      "808": 1,
      "811": 1,
      "814": 1,
      "816": 5,
      "818": 1,
      "822": 1,
      "824": 1,
      "828": 1,
      "831": 1,
      "857": 1,
      "882": 1,
      "886": 1,
      "896": 2,
      "917": 1,
      "932": 1,
      "952": 1,
      "959": 1,
      "960": 1,
      "1013": 1,
      "1052": 1,
      "1053": 2,
      "1113": 1,
      "1120": 1,
      "1124": 1,
      "1139": 1,
      "1187": 1,
      "1189": 1,
      "1191": 1,
      "1204": 1,
      "1222": 1,
      "1238": 1,
      "1239": 1,
      "1241": 1,
      "1246": 1,
      "1259": 1,
      "1283": 1,
      "1286": 1,
      "1314": 1,
      "1317": 1,
      "1324": 1,
      "1348": 1,
      "1386": 1,
      "1389": 1,
      "1403": 1,
      "1416": 1,
      "1458": 1,
      "1463": 1,
      "1466": 1,
      "1474": 1,
      "1537": 1,
      "1548": 1,
      "1572": 1,
      "1605": 1,
      "1630": 1,
      "1645": 1,
      "1689": 1,
      "1705": 1,
      "1721": 1,
      "1741": 1,
      "1835": 1,
      "1839": 1,
      "1874": 1,
      "1896": 1,
      "1934": 1,
      "2020": 1,
      "2022": 1,
      "2035": 1,
      "2051": 1,
      "2122": 1,
      "2195": 1,
      "2198": 1,
      "2311": 1,
      "2313": 1,
      "2319": 1,
      "2344": 1,
      "2349": 1,
      "2353": 1,
      "2356": 1,
      "2361": 1,
      "2392": 1,
      "2409": 1,
      "2430": 1,
      "2432": 1,
      "2450": 1,
      "2489": 1,
      "2510": 1,
      "2532": 2,
      "2539": 1,
      "2547": 1,
      "2564": 1,
      "2576": 1,
      "2586": 1,
      "2587": 1,
      "2598": 1,
      "2614": 1,
      "2623": 1,
      "2627": 1,
      "2629": 1,
      "2641": 1,
      "2657": 1,
      "2658": 1,
      "2677": 1,
      "2686": 1,
      "2692": 1,
      "2700": 1,
      "2712": 1,
      "2713": 1,
      "2760": 1,
      "2765": 1,
      "2779": 1,
      "2780": 1,
      "2794": 2,
      "2799": 1,
      "2802": 2,
      "2804": 2,
      "2806": 1,
      "2807": 1,
      "2809": 2,
      "2812": 1,
      "2814": 1,
      "2815": 1,
      "2819": 1,
      "2820": 1,
      "2821": 1,
      "2824": 1,
      "2825": 1,
      "2828": 1,
      "2832": 2,
      "2841": 1,
      "2842": 1,
      "2845": 1,
      "2849": 1,
      "2853": 2,
      "2854": 1,
      "2856": 1,
      "2859": 1,
      "2863": 1,
      "2864": 1,
      "2868": 1,
      "2872": 1,
      "2873": 1,
      "2875": 3,
      "2877": 1,
      "2889": 1,
      "2892": 1,
      "2894": 2,
      "2899": 1,
      "2901": 1,
      "2914": 1,
      "2918": 1,
      "2922": 1,
      "2926": 1,
      "2929": 2,
      "2930": 1,
      "2931": 1,
      "2935": 1,
      "2942": 2,
      "2946": 1,
      "2948": 1,
      "2949": 1,
      "2950": 1,
      "2951": 1,
      "2955": 1,
      "2956": 1,
      "2959": 1,
      "2960": 1,
      "2962": 1,
      "2969": 1,
      "2973": 1,
      "2974": 1,
      "2976": 1,
      "2978": 1,
      "2981": 1,
      "2984": 1,
      "2985": 1,
      "2989": 1,
      "2995": 1,
      "2997": 1,
      "3010": 1,
      "3015": 1,
      "3017": 1,
      "3018": 1,
      "3022": 1,
      "3023": 1,
      "3024": 1,
      "3026": 1,
      "3034": 1,
      "3037": 2,
      "3040": 1,
      "3045": 1,
      "3056": 1,
      "3058": 1,
      "3069": 1,
      "3080": 1,
      "3083": 1,
      "3086": 1,
      "3088": 1,
      "3090": 1,
      "3107": 1,
      "3120": 1,
      "3122": 1,
      "3133": 1,
      "3151": 1,
      "3203": 1,
      "3208": 1,
      "3216": 1,
      "3219": 1,
      "3235": 1,
      "3236": 1,
      "3244": 1,
      "3252": 1,
      "3281": 1,
      "3292": 1,
      "3333": 1,
      "3346": 1,
      "3447": 1,
      "3448": 1,
      "3484": 1,
      "3630": 2,
      "3632": 1,
      "3642": 2,
      "3647": 1,
      "3675": 1,
      "3705": 1,
      "3709": 1,
      "3719": 1,
      "3721": 1,
      "3723": 2,
      "3726": 1,
      "3740": 1,
      "3741": 1,
      "3743": 1,
      "3745": 1,
      "3748": 1,
      "3749": 1,
      "3751": 1,
      "3753": 1,
      "3757": 1,
      "3758": 1,
      "3763": 1,
      "3765": 1,
      "3767": 1,
      "3771": 1,
      "3779": 1,
      "3783": 1,
      "3785": 3,
      "3786": 3,
      "3797": 1,
      "3798": 1,
      "3802": 1,
      "3803": 1,
      "3804": 1,
      "3817": 2,
      "3824": 1,
      "3829": 1,
      "3830": 1,
      "3836": 1,
      "3840": 1,
      "3843": 1,
      "3846": 1,
      "3847": 1,
      "3853": 2,
      "3856": 1,
      "3860": 1,
      "3861": 2,
      "3862": 1,
      "3866": 1,
      "3871": 1,
      "3877": 1,
      "3878": 1,
      "3879": 1,
      "3887": 2,
      "3888": 2,
      "3889": 1,
      "3890": 1,
      "3891": 1,
      "3892": 1,
      "3894": 1,
      "3895": 1,
      "3896": 1,
      "3897": 1,
      "3898": 1,
      "3899": 1,
      "3900": 2,
      "3904": 1,
      "3906": 1,
      "3907": 4,
      "3908": 1,
      "3909": 3,
      "3910": 2,
      "3911": 1,
      "3912": 1,
      "3914": 1,
      "3915": 2,
      "3916": 1,
      "3917": 2,
      "3918": 2,
      "3919": 3,
      "3920": 2,
      "3921": 2,
      "3922": 1,
      "3923": 1,
      "3924": 3,
      "3925": 2,
      "3927": 2,
      "3930": 2,
      "3932": 2,
      "3933": 1,
      "3934": 2,
      "3935": 2,
      "3936": 4,
      "3937": 2,
      "3938": 2,
      "3939": 5,
      "3940": 5,
      "3942": 3,
      "3943": 2,
      "3944": 3,
      "3945": 11,
      "3946": 4,
      "3947": 6,
      "3948": 12,
      "3949": 4,
      "3950": 7,
      "3951": 3,
      "3952": 5,
      "3953": 4,
      "3954": 6,
      "3955": 3,
      "3956": 4,
      "3957": 5,
      "3958": 2,
      "3959": 6,
      "3960": 7,
      "3961": 4,
      "3962": 3,
      "3963": 7,
      "3964": 8,
      "3965": 3,
      "3966": 4,
      "3967": 4,
      "3968": 6,
      "3969": 5,
      "3970": 3,
      "3971": 2,
      "3972": 7,
      "3973": 3,
      "3974": 1,
      "3975": 7,
      "3976": 2,
      "3978": 5,
      "3979": 1,
      "3980": 3,
      "3981": 4,
      "3983": 2,
      "3984": 5,
      "3985": 5,
      "3986": 1,
      "3988": 4,
      "3989": 4,
      "3990": 4,
      "3991": 3,
      "3992": 7,
      "3993": 2,
      "3994": 4,
      "3995": 3,
      "3996": 1,
      "3997": 2,
      "3998": 3,
      "3999": 1,
      "4000": 1,
      "4001": 4,
      "4002": 3,
      "4003": 2,
      "4004": 6,
      "4005": 2,
      "4006": 1,
      "4007": 1,
      "4008": 2,
      "4009": 3,
      "4011": 2,
      "4012": 2,
      "4013": 1,
      "4014": 2,
      "4016": 2,
      "4017": 2,
      "4018": 1,
      "4019": 1,
      "4020": 4,
      "4022": 4,
      "4023": 2,
      "4024": 4,
      "4026": 2,
      "4027": 3,
      "4028": 3,
      "4029": 1,
      "4030": 3,
      "4031": 2,
      "4032": 2,
      "4033": 1,
      "4034": 1,
      "4035": 4,
      "4037": 2,
      "4038": 1,
      "4039": 1,
      "4040": 1,
      "4045": 1,
      "4046": 1,
      "4047": 1,
      "4048": 2,
      "4051": 2,
      "4054": 1,
      "4056": 1,
      "4057": 1,
      "4058": 1,
      "4060": 1,
      "4061": 1,
      "4063": 2,
      "4065": 2,
      "4066": 2,
      "4067": 2,
      "4068": 1,
      "4069": 1,
      "4073": 2,
      "4075": 2,
      "4076": 1,
      "4078": 1,
      "4079": 1,
      "4080": 1,
      "4081": 1,
      "4083": 2,
      "4084": 1,
      "4086": 1,
      "4087": 1,
      "4089": 1,
      "4090": 1,
      "4092": 1,
      "4093": 2,
      "4095": 1,
      "4096": 2,
      "4097": 1,
      "4098": 2,
      "4099": 3,
      "4100": 1,
      "4101": 1,
      "4102": 2,
      "4106": 140
   },
   "wasClean": true,
   "wasCloseHandshakeTimeout": false,
   "wasNotCleanReason": null,
   "wasOpenHandshakeTimeout": false,
   "wasServerConnectionDropTimeout": false,
   "wirelog": [
      [
         "RO",
         [
            300,
            "474554202f72756e436173653f636173653d333830266167656e743d636f6d2e7a776f70706c652e5053576562536f636b657420485454502f312e310d0a486f ..."
         ]
      ],
      [
         "TO",
         [
            252,
            "485454502f312e312031303120537769746368696e672050726f746f636f6c730d0a5365727665723a204175746f6261686e5465737453756974652f302e372e ..."
         ],
         false
      ],
      [
         "WLM",
         false
      ],
      [
         "TI",
         480
      ],
      [
         "WLM",
         true
      ],
      [
         "TF",
         [
            2,
            "0x03e8"
         ],
         8,
         true,
         0,
         null,
         null,
         null,
         false
      ],
      [
         "TO",
         [
            4,
            "880203e8"
         ],
         false
      ],
      [
         "RO",
         [
            8,
            "8882a4e4e929a70c"
         ]
      ],
      [
         "RF",
         [
            2,
            "0x03e8"
         ],
         8,
         true,
         0,
         true,
         "a4e4e929"
      ]
   ]
}